MANIFEST.in
README.md
setup.py
lopper/VERSION
lopper/__init__.py
lopper/__main__.py
lopper/base.py
lopper/dt.py
lopper/fdt.py
lopper/fmt.py
lopper/lopper.ini
lopper/query.py
lopper/rest.py
lopper/tree.py
lopper/yaml.py
lopper.egg-info/PKG-INFO
lopper.egg-info/SOURCES.txt
lopper.egg-info/dependency_links.txt
lopper.egg-info/entry_points.txt
lopper.egg-info/namespace_packages.txt
lopper.egg-info/requires.txt
lopper.egg-info/top_level.txt
lopper/assists/README
lopper/assists/baremetal_bspconfig_xlnx.py
lopper/assists/baremetal_gentestapp_xlnx.py
lopper/assists/baremetal_xparameters_xlnx.py
lopper/assists/baremetalconfig_xlnx.py
lopper/assists/baremetaldrvlist_xlnx.py
lopper/assists/baremetallinker_xlnx.py
lopper/assists/bmcmake_metadata_xlnx.py
lopper/assists/cdo.py
lopper/assists/cdo_topology.py
lopper/assists/cdotypes.py
lopper/assists/domain-access.py
lopper/assists/grep.py
lopper/assists/lopper_lib.py
lopper/assists/openamp-xlnx-zynq.py
lopper/assists/openamp-xlnx.py
lopper/assists/openamp.py
lopper/assists/openamp_xlnx_common.py
lopper/assists/subsystem.py
lopper/assists/topology_headr.py
lopper/assists/xlnx_overlay_dt.py
lopper/assists/zuplus_config.py
lopper/assists/zuplus_xppu_config.py
lopper/assists/zuplus_xppu_default.py
lopper/assists/xlnx/cdogen.py
lopper/assists/xlnx/ftb.py
lopper/assists/xlnx/power.py
lopper/assists/xlnx/protections.py
lopper/assists/xlnx/subsystem.py
lopper/assists/xlnx/xmpu.py
lopper/assists/xlnx/xppu.py
lopper/lops/README
lopper/lops/lop-a53-imux.dts
lopper/lops/lop-a72-imux.dts
lopper/lops/lop-bin.dts
lopper/lops/lop-delete-chosen.dts
lopper/lops/lop-domain-a53.dts
lopper/lops/lop-domain-a72.dts
lopper/lops/lop-domain-linux-a53.dts
lopper/lops/lop-domain-linux.dts
lopper/lops/lop-domain-r5-zynqmp.dts
lopper/lops/lop-domain-r5.dts
lopper/lops/lop-domain-simple.dts
lopper/lops/lop-domain-zephyr.dts
lopper/lops/lop-load.dts
lopper/lops/lop-openamp-versal.dts
lopper/lops/lop-r5-imux.dts
lopper/lops/lop-versal-cdo-hook.dts
lopper/lops/lop-versal-cdo-prot-custom.dts
lopper/lops/lop-versal-cdo-prot-enable.dts
lopper/lops/lop-versal-regulator-cdo.dts
lopper/lops/lop-versal-vck190_apu_sub-xilpm_subsystem.dts
