Metadata-Version: 2.1
Name: lopper
Version: 0.2020.6
Summary: A devicetree pruner
Home-page: https://github.com/devicetree-org/lopper
Author: Bruce Ashfield
Author-email: bruce.ashfield@gmail.com
License: BSD
Platform: UNKNOWN
Classifier: Programming Language :: Python :: 3
Classifier: License :: OSI Approved :: BSD License
Classifier: Operating System :: POSIX :: Linux
Requires-Python: >=3.5
Provides-Extra: server
Provides-Extra: yaml
Provides-Extra: dt
Provides-Extra: pcpp
